trulens_eval/Leaderboard.py
trulens_eval/__init__.py
trulens_eval/_utils/optional.py
trulens_eval/app.py
trulens_eval/appui.py
trulens_eval/database/__init__.py
trulens_eval/database/base.py
trulens_eval/database/exceptions.py
trulens_eval/database/migrations/__init__.py
trulens_eval/database/migrations/data.py
trulens_eval/database/orm.py
trulens_eval/database/sqlalchemy.py
trulens_eval/database/utils.py
trulens_eval/feedback/__init__.py
trulens_eval/feedback/embeddings.py
trulens_eval/feedback/feedback.py
trulens_eval/feedback/groundtruth.py
trulens_eval/feedback/prompts.py
trulens_eval/feedback/provider/__init__.py
trulens_eval/feedback/provider/base.py
trulens_eval/feedback/provider/bedrock.py
trulens_eval/feedback/provider/cortex.py
trulens_eval/feedback/provider/endpoint/__init__.py
trulens_eval/feedback/provider/endpoint/base.py
trulens_eval/feedback/provider/endpoint/bedrock.py
trulens_eval/feedback/provider/endpoint/cortex.py
trulens_eval/feedback/provider/endpoint/google.py
trulens_eval/feedback/provider/endpoint/hugs.py
trulens_eval/feedback/provider/endpoint/langchain.py
trulens_eval/feedback/provider/endpoint/litellm.py
trulens_eval/feedback/provider/endpoint/openai.py
trulens_eval/feedback/provider/google.py
trulens_eval/feedback/provider/hugs.py
trulens_eval/feedback/provider/langchain.py
trulens_eval/feedback/provider/litellm.py
trulens_eval/feedback/provider/openai.py
trulens_eval/generate_test_set.py
trulens_eval/guardrails/__init__.py
trulens_eval/guardrails/base.py
trulens_eval/guardrails/langchain.py
trulens_eval/guardrails/llama.py
trulens_eval/instruments.py
trulens_eval/keys.py
trulens_eval/react_components/__init__.py
trulens_eval/react_components/record_viewer/__init__.py
trulens_eval/schema/__init__.py
trulens_eval/schema/app.py
trulens_eval/schema/base.py
trulens_eval/schema/feedback.py
trulens_eval/schema/record.py
trulens_eval/schema/types.py
trulens_eval/streamlit.py
trulens_eval/tru.py
trulens_eval/tru_basic_app.py
trulens_eval-2.5.0.dist-info/METADATA
trulens_eval-2.5.0.dist-info/WHEEL
trulens_eval-2.5.0.dist-info/RECORD
